flaskErrorHandler/__init__.py
flaskErrorHandler-0.3.dist-info/LICENSE
flaskErrorHandler-0.3.dist-info/METADATA
flaskErrorHandler-0.3.dist-info/WHEEL
flaskErrorHandler-0.3.dist-info/top_level.txt
flaskErrorHandler-0.3.dist-info/RECORD
