Metadata-Version: 2.1
Name: flaskErrorHandler
Version: 0.3
Summary: A flask package to handle exception and notify on gmail
Home-page: https://github.com/parmeshashwath/flaskErrorHandler
Author: Parmesh Ashwath
Author-email: parmesh20120@gmail.com
License: UNKNOWN
Platform: UNKNOWN
Classifier: Programming Language :: Python :: 3
Classifier: License :: OSI Approved :: MIT License
Classifier: Operating System :: OS Independent
Requires-Python: >=3.6
